{
  "migrations": [
    {
      "cli": "nx",
      "version": "17.3.0-beta.6",
      "description": "Updates the nx wrapper.",
      "implementation": "./src/migrations/update-17-3-0/update-nxw",
      "package": "nx",
      "name": "17.3.0-update-nx-wrapper"
    },
    {
      "cli": "nx",
      "version": "18.0.0-beta.2",
      "description": "Updates .env to disabled adding plugins when generating projects in an existing Nx workspace",
      "implementation": "./src/migrations/update-18-0-0/disable-crystal-for-existing-workspaces",
      "x-repair-skip": true,
      "package": "nx",
      "name": "18.0.0-disable-adding-plugins-for-existing-workspaces"
    },
    {
      "cli": "nx",
      "version": "17.3.1-beta.0",
      "description": "Add project property to playwright config",
      "implementation": "./src/migrations/update-17-3-1/add-project-to-config",
      "package": "@nx/playwright",
      "name": "17-3-1-add-project-to-config"
    },
    {
      "cli": "nx",
      "version": "18.0.0-beta.0",
      "description": "Add NX_MF_DEV_SERVER_STATIC_REMOTES to inputs for task hashing when '@nx/webpack:webpack' is used for Module Federation.",
      "factory": "./src/migrations/update-18-0-0/add-mf-env-var-to-target-defaults",
      "package": "@nx/react",
      "name": "add-module-federation-env-var-to-target-defaults"
    },
    {
      "cli": "nx",
      "version": "17.2.6-beta.1",
      "description": "Rename workspace rules from @nx/workspace/name to @nx/workspace-name",
      "implementation": "./src/migrations/update-17-2-6-rename-workspace-rules/rename-workspace-rules",
      "package": "@nx/eslint-plugin",
      "name": "update-17-2-6-rename-workspace-rules"
    },
    {
      "version": "17.1.0-beta.1",
      "description": "Updates for @typescript-utils/utils v6.9.1+",
      "implementation": "./src/migrations/update-17-1-0/update-typescript-eslint",
      "package": "@nx/eslint",
      "name": "update-typescript-eslint"
    },
    {
      "version": "17.2.0-beta.0",
      "description": "Simplify eslintFilePatterns",
      "implementation": "./src/migrations/update-17-2-0/simplify-eslint-patterns",
      "package": "@nx/eslint",
      "name": "simplify-eslint-patterns"
    },
    {
      "version": "17.2.9",
      "description": "Move executor options to target defaults",
      "implementation": "./src/migrations/update-17-2-9/move-options-to-target-defaults",
      "package": "@nx/eslint",
      "name": "move-options-to-target-defaults"
    },
    {
      "cli": "nx",
      "version": "17.2.1-beta.0",
      "description": "Add webpack.config.js file when webpackConfig is not defined",
      "implementation": "./src/migrations/update-17-2-1/webpack-config-setup",
      "package": "@nx/webpack",
      "name": "update-17-2-1-webpack-config-setup"
    },
    {
      "version": "17.1.0-beta.2",
      "description": "Move target defaults",
      "implementation": "./src/migrations/update-17-1-0/move-target-defaults",
      "package": "@nx/vite",
      "name": "move-target-defaults"
    },
    {
      "version": "17.2.0-beta.10",
      "description": "Update vite config.",
      "implementation": "./src/migrations/update-17-2-0/update-vite-config",
      "package": "@nx/vite",
      "name": "update-vite-config"
    },
    {
      "version": "17.3.0-beta.0",
      "description": "Move the vitest coverage thresholds in their own object if exists and add reporters.",
      "implementation": "./src/migrations/update-17-3-0/vitest-coverage-and-reporters",
      "package": "@nx/vite",
      "name": "vitest-coverage-and-reporters"
    },
    {
      "version": "17.1.0-beta.2",
      "description": "Move jest executor options to nx.json targetDefaults",
      "implementation": "./src/migrations/update-17-1-0/move-options-to-target-defaults",
      "package": "@nx/jest",
      "name": "move-options-to-target-defaults"
    },
    {
      "cli": "nx",
      "version": "17.2.7",
      "description": "Remove patched eslint rule for @next/next/no-html-link-for-pages",
      "implementation": "./src/migrations/update-17-2-7/remove-eslint-rules-patch",
      "package": "@nx/next",
      "name": "update-17-2-7"
    }
  ]
}
