{
  "id": "410edddc-dbbf-5d80-9c82-759f9d13096b",
  "name": "Conduit",
  "values": [
    {
      "enabled": true,
      "key": "apiUrl",
      "value": "https://conduit.productionready.io/api",
      "type": "text"
    },
    {
      "enabled": true,
      "key": "token",
      "value": "",
      "type": "text"
    }
  ],
  "timestamp": 1489786196110,
  "_postman_variable_scope": "environment",
  "_postman_exported_at": "2017-03-17T21:30:01.555Z",
  "_postman_exported_using": "Postman/4.10.3"
}
